redash_lite/__init__.py
redash_lite/client.py
redash_lite-0.1.0.dist-info/licenses/LICENSE.txt
redash_lite-0.1.0.dist-info/METADATA
redash_lite-0.1.0.dist-info/WHEEL
redash_lite-0.1.0.dist-info/top_level.txt
redash_lite-0.1.0.dist-info/RECORD
