Metadata-Version: 2.4
Name: redash_lite
Version: 0.1.0
Summary: Tiny client to trigger Redash queries and fetch fresh results
Author-email: Your Name <you@example.com>
Requires-Python: >=3.7
License-File: LICENSE.txt
Requires-Dist: requests
Dynamic: license-file
